[
  {
    "ContainingType": "SalonSystemAPI.Controllers.AuthController",
    "Method": "Login",
    "RelativePath": "api/Auth/login",
    "HttpMethod": "POST",
    "IsController": true,
    "Order": 0,
    "Parameters": [
      {
        "Name": "dto",
        "Type": "SalonSystemAPI.Models.DTO.LoginDto",
        "IsRequired": true
      }
    ],
    "ReturnTypes": []
  },
  {
    "ContainingType": "SalonSystemAPI.Controllers.OrganizationsController",
    "Method": "Create",
    "RelativePath": "api/Organizations",
    "HttpMethod": "POST",
    "IsController": true,
    "Order": 0,
    "Parameters": [
      {
        "Name": "dto",
        "Type": "SalonSystemAPI.Models.DTO.CreateOrganizationDto",
        "IsRequired": true
      }
    ],
    "ReturnTypes": []
  },
  {
    "ContainingType": "SalonSystemAPI.Controllers.OrganizationsController",
    "Method": "JoinByCode",
    "RelativePath": "api/Organizations/join",
    "HttpMethod": "POST",
    "IsController": true,
    "Order": 0,
    "Parameters": [
      {
        "Name": "dto",
        "Type": "SalonSystemAPI.Models.DTO.JoinByCodeDto",
        "IsRequired": true
      }
    ],
    "ReturnTypes": []
  },
  {
    "ContainingType": "SalonSystemAPI.Controllers.OrganizationsController",
    "Method": "GetMyOrganizations",
    "RelativePath": "api/Organizations/mine",
    "HttpMethod": "GET",
    "IsController": true,
    "Order": 0,
    "Parameters": [],
    "ReturnTypes": []
  },
  {
    "ContainingType": "SalonSystemAPI.Controllers.UsersController",
    "Method": "Register",
    "RelativePath": "api/Users/register",
    "HttpMethod": "POST",
    "IsController": true,
    "Order": 0,
    "Parameters": [
      {
        "Name": "dto",
        "Type": "SalonSystemAPI.Models.DTO.RegisterDto",
        "IsRequired": true
      }
    ],
    "ReturnTypes": []
  }
]